kitty_maze-1.1.1.dist-info/licenses/LICENSE
maze/__init__.py
maze/interactions.py
maze/main.py
maze/objects.py
maze/play_area.py
maze/play_map.py
maze/play_objects.py
maze/side_bar.py
maze/state.py
maze/walls.py
maze/img/angry_cat.png
maze/img/billboard_down.png
maze/img/billboard_left.png
maze/img/billboard_right.png
maze/img/block_E.png
maze/img/block_L.png
maze/img/block_O.png
maze/img/block_V.png
maze/img/bucket.png
maze/img/bunny.png
maze/img/bunny_prints.png
maze/img/cake.png
maze/img/doll.png
maze/img/eggplant.png
maze/img/fire.png
maze/img/fishing_rod.png
maze/img/flowers.png
maze/img/gate.png
maze/img/happy_cat.png
maze/img/house.png
maze/img/key.png
maze/img/lake.png
maze/img/matches.png
maze/img/partial_wall_horizontal.png
maze/img/partial_wall_vertical.png
maze/img/player.png
maze/img/shrubbery.png
maze/img/slotted_block_E.png
maze/img/slotted_block_L.png
maze/img/slotted_block_O.png
maze/img/slotted_block_V.png
maze/img/trash_can.png
maze/img/tree.png
maze/img/tree_apple.png
maze/img/tree_peach.png
maze/img/wall_horizontal.png
maze/img/wall_vertical.png
maze/img/item/apple.png
maze/img/item/block_E.png
maze/img/item/block_L.png
maze/img/item/block_O.png
maze/img/item/block_V.png
maze/img/item/bucket.png
maze/img/item/eggplant.png
maze/img/item/filled_bucket.png
maze/img/item/fish.png
maze/img/item/fishing_rod.png
maze/img/item/key.png
maze/img/item/matches.png
maze/img/item/peach.png
kitty_maze-1.1.1.dist-info/METADATA
kitty_maze-1.1.1.dist-info/WHEEL
kitty_maze-1.1.1.dist-info/entry_points.txt
kitty_maze-1.1.1.dist-info/top_level.txt
kitty_maze-1.1.1.dist-info/RECORD
