Metadata-Version: 2.4
Name: kitty-maze
Version: 1.1.1
Summary: kitty maze game
Project-URL: Homepage, https://github.com/rchen152/maze
Classifier: Programming Language :: Python :: 3
Classifier: License :: OSI Approved :: GNU General Public License v3 (GPLv3)
Classifier: Operating System :: POSIX :: Linux
Requires-Python: >=3.10
License-File: LICENSE
Requires-Dist: kitty-common>=0.5.5
Requires-Dist: kitty-escape>=1.3.1
Requires-Dist: pyrefly==0.40.0
Requires-Dist: pygame>=2.1.2
Provides-Extra: dev
Requires-Dist: flake8; extra == "dev"
Requires-Dist: flake8-pyproject; extra == "dev"
Requires-Dist: pytest; extra == "dev"
Dynamic: license-file
